{
  "Name": "General Locations",
  "Description": "A list of locations that can be used by the Location Plugin",
  "ScanDepth": 2,
  "ActivationDuration": 3,
  "Entries": [
    {
      "Name": "Beach",
      "Enabled": true,
      "KeyWordsMain": [ "beach", "sea", "ocean" ],
      "KeyWordsSecondary": [],
      "WordLink": "Or",
      "Position": "SystemPrompt",
      "PositionIndex": 0,
      "Priority": 100,
      "CaseSensitive": false,
      "Content": "The beach is a beautiful place to relax and enjoy the sun."
    },
    {
      "Name": "Public Restroom",
      "Enabled": true,
      "KeyWordsMain": [ "toilet", "restroom", "bathroom" ],
      "KeyWordsSecondary": [ "public" ],
      "WordLink": "And",
      "Position": "SystemPrompt",
      "PositionIndex": 0,
      "Priority": 100,
      "CaseSensitive": false,
      "Content": "The public toilets are a place where you can do your business. They are quite dirty and smelly."
    },
    {
      "Name": "Classy Restaurant",
      "Enabled": true,
      "KeyWordsMain": [ "restaurant", "dinner" ],
      "KeyWordsSecondary": [ "classy" ],
      "WordLink": "And",
      "Position": "SystemPrompt",
      "PositionIndex": 0,
      "Priority": 100,
      "CaseSensitive": false,
      "Content": "The classy restaurant is a place where you can enjoy a nice meal in a fancy setting."
    },
    {
      "Name": "Movie Theater",
      "Enabled": true,
      "KeyWordsMain": [ "movie theater", "cinema" ],
      "KeyWordsSecondary": [],
      "WordLink": "Or",
      "Position": "SystemPrompt",
      "PositionIndex": 0,
      "Priority": 100,
      "CaseSensitive": false,
      "Content": "The movie theater is a place where you can watch the latest movies on the big screen."
    },
    {
      "Name": "Backalley Street",
      "Enabled": true,
      "KeyWordsMain": [ "backalley" ],
      "KeyWordsSecondary": [ "street" ],
      "WordLink": "And",
      "Position": "SystemPrompt",
      "PositionIndex": 0,
      "Priority": 100,
      "CaseSensitive": false,
      "Content": "The backalley street is a dark and dirty place where shady characters hang out. It's not a safe place to be at night."
    },
    {
      "Name": "Hospital",
      "Enabled": true,
      "KeyWordsMain": [ "hospital", "clinic" ],
      "KeyWordsSecondary": [],
      "WordLink": "Or",
      "Position": "SystemPrompt",
      "PositionIndex": 0,
      "Priority": 100,
      "CaseSensitive": false,
      "Content": "The hospital is a place where you can get medical treatment when you're sick or injured."
    },
    {
      "Name": "Park",
      "Enabled": true,
      "KeyWordsMain": [ "park", "garden" ],
      "KeyWordsSecondary": [],
      "WordLink": "Or",
      "Position": "SystemPrompt",
      "PositionIndex": 0,
      "Priority": 100,
      "CaseSensitive": false,
      "Content": "The local park is a beautiful place where you can relax and enjoy nature."
    },
    {
      "Name": "High School",
      "Enabled": true,
      "KeyWordsMain": [ "school", "high school" ],
      "KeyWordsSecondary": [ "university" ],
      "WordLink": "Or",
      "Position": "SystemPrompt",
      "PositionIndex": 0,
      "Priority": 100,
      "CaseSensitive": false,
      "Content": "The high school is a place where teenagers go to learn and prepare for their future careers."
    },
    {
      "Name": "Police Station",
      "Enabled": true,
      "KeyWordsMain": [ "police station", "cop shop" ],
      "KeyWordsSecondary": [],
      "WordLink": "Or",
      "Position": "SystemPrompt",
      "PositionIndex": 0,
      "Priority": 100,
      "CaseSensitive": false,
      "Content": "The police station is a place where law enforcement officers work to keep the community safe."
    },
    {
      "Name": "Supermarket",
      "Enabled": true,
      "KeyWordsMain": [ "supermarket", "grocery store", "super market" ],
      "KeyWordsSecondary": [],
      "WordLink": "Or",
      "Position": "SystemPrompt",
      "PositionIndex": 0,
      "Priority": 100,
      "CaseSensitive": false,
      "Content": "The supermarket is a place where you can buy food and other household items."
    },
    {
      "Name": "Library",
      "Enabled": true,
      "KeyWordsMain": [ "library", "bookstore" ],
      "KeyWordsSecondary": [],
      "WordLink": "Or",
      "Position": "SystemPrompt",
      "PositionIndex": 0,
      "Priority": 100,
      "CaseSensitive": false,
      "Content": "The library is a place where you can borrow books and study in a quiet environment."
    },
    {
      "Name": "Sex Shop",
      "Enabled": true,
      "KeyWordsMain": [ "sex shop", "sexshop" ],
      "KeyWordsSecondary": [],
      "WordLink": "Or",
      "Position": "SystemPrompt",
      "PositionIndex": 0,
      "Priority": 100,
      "CaseSensitive": false,
      "Message": "The sex shop is a good location to buy adult toys and other sexual items. It's located in a shady part of town."
    },
    {
      "Name": "Strip Club",
      "Enabled": true,
      "KeyWordsMain": [ "strip club", "stripclub" ],
      "KeyWordsSecondary": [],
      "WordLink": "Or",
      "Position": "SystemPrompt",
      "PositionIndex": 0,
      "Priority": 100,
      "CaseSensitive": false,
      "Content": "The strip club is a place where you can watch strippers perform on stage. It's a popular spot for bachelor parties."
    },
    {
      "Name": "Swimming Pool",
      "Enabled": true,
      "KeyWordsMain": [ "swimming pool", "pool" ],
      "KeyWordsSecondary": [],
      "WordLink": "Or",
      "Position": "SystemPrompt",
      "PositionIndex": 0,
      "Priority": 100,
      "CaseSensitive": false,
      "Content": "The swimming pool is a place where you can swim and relax in the water. It's a popular spot for families and children."
    }
  ]
}